firestone/__init__.py
firestone/__main__.py
firestone/schema/__init__.py
firestone/schema/asyncapi.jinja2
firestone/schema/cli_module.py.jinja2
firestone/schema/cli_module.rs.jinja2
firestone/schema/main.py.jinja2
firestone/schema/main.rs.jinja2
firestone/schema/openapi.jinja2
firestone/schema/resource.yaml
firestone/schema/streamlit.py.jinja2
firestone/schema/streamlit_page.py.jinja2
firestone/spec/__init__.py
firestone/spec/_base.py
firestone/spec/asyncapi.py
firestone/spec/cli.py
firestone/spec/cli_rust.py
firestone/spec/openapi.py
firestone/spec/streamlit.py
firestoned-0.10.5.dist-info/METADATA
firestoned-0.10.5.dist-info/WHEEL
firestoned-0.10.5.dist-info/entry_points.txt
firestoned-0.10.5.dist-info/licenses/LICENSE
firestoned-0.10.5.dist-info/RECORD
