Metadata-Version: 2.4
Name: firestoned
Version: 0.10.5
Summary: Build OpenAPI and AsyncAPI specs based off one or more resource json schema files
License: Apache 2.0
License-File: LICENSE
Author: Erick Bourgeois
Author-email: erick@jeb.ca
Requires-Python: >=3.9, !=2.7.*, !=3.0.*, !=3.1.*, !=3.2.*, !=3.3.*, !=3.4.*, !=3.5.*, !=3.6.*, !=3.7.*, !=3.8.*
Classifier: License :: Other/Proprietary License
Classifier: Programming Language :: Python :: 3
Classifier: Programming Language :: Python :: 3.9
Classifier: Programming Language :: Python :: 3.10
Classifier: Programming Language :: Python :: 3.11
Classifier: Programming Language :: Python :: 3.12
Classifier: Programming Language :: Python :: 3.13
Classifier: Programming Language :: Python :: 3.14
Provides-Extra: caching
Requires-Dist: Jinja2 (>=3.1.2)
Requires-Dist: aiohttp (>=3.8.4)
Requires-Dist: click (>=8.1.3)
Requires-Dist: diff-match-patch (>=20230430)
Requires-Dist: firestone-lib (>=0.1.0)
Requires-Dist: jsonref (>=1.0.0.post1)
Requires-Dist: jsonschema (>=4.16.0)
Requires-Dist: pydantic (>=1.10.5)
Requires-Dist: python-dateutil (>=2.8.2)
Requires-Dist: pyyaml (>=6.0)
Requires-Dist: quart (>=0.18.3,<0.19.0) ; extra == "caching"
Project-URL: Repository, https://github.com/firestoned/firestone
